jitcsim/__init__.py
jitcsim/networks.py
jitcsim/utility.py
jitcsim/visualization.py
jitcsim/models/__init__.py
jitcsim/models/damp_oscillator.py
jitcsim/models/kuramoto_dde.py
jitcsim/models/kuramoto_ode.py
jitcsim/models/kuramoto_sde.py
jitcsim/models/montbrio.py
jitcsim-0.3.dist-info/LICENSE
jitcsim-0.3.dist-info/METADATA
jitcsim-0.3.dist-info/WHEEL
jitcsim-0.3.dist-info/top_level.txt
jitcsim-0.3.dist-info/RECORD
