Metadata-Version: 2.1
Name: jitcsim
Version: 0.3
Summary: Simulation of networks with Ordinary/Delay/Stochastic differential equations (just-in-time compilation
Home-page: https://github.com/Ziaeemehr/JITCSIM
Author: ...
Author-email: a.ziaeemehr@gmail.com
License: UNKNOWN
Platform: UNKNOWN
Classifier: Programming Language :: Python :: 3
Classifier: License :: OSI Approved :: MIT License
Classifier: Operating System :: OS Independent
Requires-Python: >=3.8
Requires-Dist: wheel
Requires-Dist: numpy
Requires-Dist: scipy
Requires-Dist: sympy
Requires-Dist: cython
Requires-Dist: numba
Requires-Dist: jitcode
Requires-Dist: jitcdde
Requires-Dist: jitcsde
Requires-Dist: networkx
Requires-Dist: matplotlib
